plume/__init__.py
plume/connection.py
plume/errors.py
plume/fields.py
plume/hooks.py
plume/resource.py
plume/schema.py
plume/storage.py
plume-0.1.0.dist-info/DESCRIPTION.rst
plume-0.1.0.dist-info/METADATA
plume-0.1.0.dist-info/RECORD
plume-0.1.0.dist-info/WHEEL
plume-0.1.0.dist-info/metadata.json
plume-0.1.0.dist-info/top_level.txt
