Metadata-Version: 2.0
Name: plume
Version: 0.1.0
Summary: Easy webapps with falcon & mongodb
Home-page: https://github.com/JamesRamm/plume
Author: James Ramm
Author-email: jamessramm@gmail.com
License: GNU General Public License v3
Keywords: plume
Platform: UNKNOWN
Classifier: Development Status :: 2 - Pre-Alpha
Classifier: Intended Audience :: Developers
Classifier: License :: OSI Approved :: GNU General Public License v3 (GPLv3)
Classifier: Natural Language :: English
Classifier: Programming Language :: Python :: 2
Classifier: Programming Language :: Python :: 2.6
Classifier: Programming Language :: Python :: 2.7
Classifier: Programming Language :: Python :: 3
Classifier: Programming Language :: Python :: 3.3
Classifier: Programming Language :: Python :: 3.4
Classifier: Programming Language :: Python :: 3.5
Requires-Dist: marshmallow (==2.13.6)
Requires-Dist: pymongo (==3.5.1)
Requires-Dist: falcon (==1.3.0)
Requires-Dist: simplejson (==3.11.1)
